pyhausbus/ABusFeature.py
pyhausbus/BusDataMessage.py
pyhausbus/BusHandler.py
pyhausbus/GenericBusData.py
pyhausbus/HausBusCommand.py
pyhausbus/HausBusUtils.py
pyhausbus/HomeServer.py
pyhausbus/IBusDataListener.py
pyhausbus/IBusDeviceListener.py
pyhausbus/Main.py
pyhausbus/ObjectId.py
pyhausbus/ResultWorker.py
pyhausbus/Templates.py
pyhausbus/UdpReceiveWorker.py
pyhausbus/WeekTime.py
pyhausbus/de/_init_.py
pyhausbus/de/hausbus/_init_.py
pyhausbus/de/hausbus/homeassistant/_init_.py
pyhausbus/de/hausbus/homeassistant/proxy/AnalogEingang.py
pyhausbus/de/hausbus/homeassistant/proxy/Controller.py
pyhausbus/de/hausbus/homeassistant/proxy/Counter.py
pyhausbus/de/hausbus/homeassistant/proxy/CurrentReader.py
pyhausbus/de/hausbus/homeassistant/proxy/DaliLine.py
pyhausbus/de/hausbus/homeassistant/proxy/DigitalPort.py
pyhausbus/de/hausbus/homeassistant/proxy/Dimmer.py
pyhausbus/de/hausbus/homeassistant/proxy/Drucksensor.py
pyhausbus/de/hausbus/homeassistant/proxy/Ethernet.py
pyhausbus/de/hausbus/homeassistant/proxy/Feuchtesensor.py
pyhausbus/de/hausbus/homeassistant/proxy/Gateway.py
pyhausbus/de/hausbus/homeassistant/proxy/Helligkeitssensor.py
pyhausbus/de/hausbus/homeassistant/proxy/IRSensor.py
pyhausbus/de/hausbus/homeassistant/proxy/Led.py
pyhausbus/de/hausbus/homeassistant/proxy/LogicalButton.py
pyhausbus/de/hausbus/homeassistant/proxy/ModBusMaster.py
pyhausbus/de/hausbus/homeassistant/proxy/ModbusSlave.py
pyhausbus/de/hausbus/homeassistant/proxy/PCA9555.py
pyhausbus/de/hausbus/homeassistant/proxy/PCServer.py
pyhausbus/de/hausbus/homeassistant/proxy/PIDController.py
pyhausbus/de/hausbus/homeassistant/proxy/PT1000.py
pyhausbus/de/hausbus/homeassistant/proxy/PowerMeter.py
pyhausbus/de/hausbus/homeassistant/proxy/ProxyFactory.py
pyhausbus/de/hausbus/homeassistant/proxy/RFIDReader.py
pyhausbus/de/hausbus/homeassistant/proxy/RGBDimmer.py
pyhausbus/de/hausbus/homeassistant/proxy/Rollladen.py
pyhausbus/de/hausbus/homeassistant/proxy/Schalter.py
pyhausbus-1.0.39.dist-info/LICENSE
pyhausbus-1.0.39.dist-info/METADATA
pyhausbus-1.0.39.dist-info/WHEEL
pyhausbus-1.0.39.dist-info/RECORD
