Metadata-Version: 2.1
Name: pyhausbus
Version: 1.0.39
Summary: Python based library for accessing haus-bus.de modules. Inteded to be used in a Home Assistant integration.
Home-page: https://www.haus-bus.de/
Author: Hermann Hoeschen
Author-email: info@haus-bus.de
Classifier: License :: OSI Approved :: MIT License
Classifier: Operating System :: OS Independent
Classifier: Programming Language :: Python :: 2
Classifier: Programming Language :: Python :: 2.7
Classifier: Programming Language :: Python :: 3
Classifier: Programming Language :: Python :: 3.4
Classifier: Programming Language :: Python :: 3.5
Classifier: Programming Language :: Python :: 3.6
Classifier: Programming Language :: Python :: 3.7
Classifier: Programming Language :: Python :: 3.8
Classifier: Programming Language :: Python :: 3.9
Classifier: Programming Language :: Python :: 3.10
Classifier: Programming Language :: Python :: 3.11
Classifier: Programming Language :: Python :: 3.12
Classifier: Programming Language :: Python :: 3.13
Project-URL: Bug Tracker, https://github.com/hausbus/homeassistant/issues
Project-URL: Repository, https://github.com/hausbus/homeassistant
